fuefit-0.0.6.dist-info/RECORD
fuefit-0.0.6.dist-info/zip-safe
fuefit-0.0.6.dist-info/metadata.json
fuefit-0.0.6.dist-info/WHEEL
fuefit-0.0.6.dist-info/DESCRIPTION.rst
fuefit-0.0.6.dist-info/METADATA
fuefit-0.0.6.dist-info/top_level.txt
fuefit-0.0.6.dist-info/entry_points.txt
fuefit/utils.py
fuefit/datamodel.py
fuefit/processor.py
fuefit/__init__.py
fuefit/mymock.py
fuefit/pdcalc.py
fuefit/_version.py
fuefit/__main__.py
fuefit/excel/FuefitExcelRunner.xlsm
fuefit/excel/.gitignore
fuefit/excel/FuefitExcelRunner.py
fuefit/excel/__init__.py
fuefit/excel/xlwings_pandalon.vba
fuefit/excel/pandalon.vba
fuefit/excel/ExcelPython.ico
fuefit/test/.gitignore
fuefit/test/datamodel_test.py
fuefit/test/Dependencies_harvest_test.py
fuefit/test/excel_test.py
fuefit/test/run_sample.bat
fuefit/test/__init__.py
fuefit/test/redirect.py
fuefit/test/FuelFit_real.csv
fuefit/test/Dependencies_plan_test.py
fuefit/test/FuelFit_real.xlsx
fuefit/test/cmdline_test.py
fuefit/test/test_table.csv
fuefit/test/run_sample.sh
fuefit/test/eng_points_full.xlsx
fuefit/test/FuelFit.xlsx
fuefit/test/engine.csv
