Metadata-Version: 2.0
Name: fuefit
Version: 0.0.6
Summary: *fuefit* fits engine-maps on physical parameters
Requires-Dist: enum34
Requires-Dist: pandas
Requires-Dist: xlrd
Requires-Dist: scipy
Requires-Dist: lmfit
Requires-Dist: jsonschema
Requires-Dist: matplotlib
Requires-Dist: networkx
Requires-Dist: pint
Requires-Dist: xlwings (==0.2.3)
